jjson2xml/__init__.py
jjson2xml/j2x.py
jjson2xml-0.1.1.dist-info/METADATA
jjson2xml-0.1.1.dist-info/WHEEL
jjson2xml-0.1.1.dist-info/top_level.txt
jjson2xml-0.1.1.dist-info/RECORD
